rolabesti/__init__.py
rolabesti/__main__.py
rolabesti/cli/__init__.py
rolabesti/cli/commands/__init__.py
rolabesti/cli/commands/config.py
rolabesti/cli/commands/copy.py
rolabesti/cli/commands/init.py
rolabesti/cli/commands/list.py
rolabesti/cli/commands/play.py
rolabesti/cli/commands/tag.py
rolabesti/cli/main.py
rolabesti/cli/options.py
rolabesti/cli/utils.py
rolabesti/config/__init__.py
rolabesti/config/settings.py
rolabesti/config/utils.py
rolabesti/controllers/__init__.py
rolabesti/controllers/config.py
rolabesti/controllers/controller.py
rolabesti/controllers/copy.py
rolabesti/controllers/init.py
rolabesti/controllers/list.py
rolabesti/controllers/parser.py
rolabesti/controllers/play.py
rolabesti/controllers/search.py
rolabesti/controllers/tag.py
rolabesti/controllers/utils.py
rolabesti/database/__init__.py
rolabesti/database/db.py
rolabesti/database/mongodb.py
rolabesti/database/tinydb.py
rolabesti/logger.py
rolabesti/models/__init__.py
rolabesti/models/filters.py
rolabesti/models/id3.py
rolabesti/models/sortings.py
rolabesti/models/track.py
rolabesti/utils.py
rolabesti/views/__init__.py
rolabesti/views/tracklist.py
rolabesti/views/utils.py
rolabesti-0.6.0.dist-info/LICENSE
rolabesti-0.6.0.dist-info/METADATA
rolabesti-0.6.0.dist-info/WHEEL
rolabesti-0.6.0.dist-info/entry_points.txt
rolabesti-0.6.0.dist-info/RECORD
