Metadata-Version: 2.1
Name: rolabesti
Version: 0.6.0
Summary: CLI app to manage, search, and play collections of mp3 tracks.
Home-page: https://github.com/kinuax/rolabesti
License: MIT
Keywords: audio,sound,music,mp3,player,id3,cli,shell,terminal,typer,click,tinydb,vlc
Author: Kinuax
Author-email: kinuax@protonmail.com
Requires-Python: >=3.10,<3.13
Classifier: Development Status :: 5 - Production/Stable
Classifier: Environment :: Console
Classifier: Framework :: Pydantic
Classifier: Framework :: Pydantic :: 2
Classifier: Framework :: Pytest
Classifier: Framework :: tox
Classifier: Intended Audience :: End Users/Desktop
Classifier: Intended Audience :: Other Audience
Classifier: License :: OSI Approved :: MIT License
Classifier: Operating System :: OS Independent
Classifier: Programming Language :: Python
Classifier: Programming Language :: Python :: 3
Classifier: Programming Language :: Python :: 3.10
Classifier: Programming Language :: Python :: 3.11
Classifier: Programming Language :: Python :: 3.12
Classifier: Topic :: Multimedia
Classifier: Topic :: Multimedia :: Sound/Audio
Classifier: Topic :: Multimedia :: Sound/Audio :: Mixers
Classifier: Topic :: Multimedia :: Sound/Audio :: Players
Classifier: Topic :: Multimedia :: Sound/Audio :: Players :: MP3
Requires-Dist: docstring-inheritance (==2.2.0)
Requires-Dist: mutagen (==1.47.0)
Requires-Dist: platformdirs (==4.2.0)
Requires-Dist: pydantic (==2.7.0)
Requires-Dist: pydantic-settings (==2.2.1)
Requires-Dist: pydub (==0.25.1)
Requires-Dist: pygame (==2.5.2)
Requires-Dist: pymongo (==4.6.2)
Requires-Dist: tinydb (==4.8.0)
Requires-Dist: tomlkit (==0.12.4)
Requires-Dist: typer (==0.12.3)
Requires-Dist: wurlitzer (==3.0.3)
Project-URL: Documentation, https://github.com/kinuax/rolabesti
Project-URL: Repository, https://github.com/kinuax/rolabesti
